dyncl/__init__.py
dyncl-0.0.0.dist-info/LICENSE
dyncl-0.0.0.dist-info/METADATA
dyncl-0.0.0.dist-info/WHEEL
dyncl-0.0.0.dist-info/top_level.txt
dyncl-0.0.0.dist-info/RECORD
