Metadata-Version: 2.1
Name: dyncl
Version: 0.0.0
Summary: Contrastive estimation of nonlinear latent dynamics
Home-page: https://github.com/dynamical-inference/dyncl
Author: Rodrigo Gonzalez Laiz, Tobias Schmidt, Steffen Schneider
Author-email: rodrigo.gonzalezlaiz@helmholtz-munich.de
Classifier: Programming Language :: Python :: 3
Requires-Python: >=3.10
License-File: LICENSE
